edsmapplotter/__init__.py
edsmapplotter/__main__.py
edsmapplotter/core.py
edsmapplotter/gui.py
edsmapplotter/resources/EDSMapPlotter_icon.ico
edsmapplotter/resources/EDSMapPlotter_icon.png
edsmapplotter-0.2.1.dist-info/licenses/LICENSE
edsmapplotter-0.2.1.dist-info/METADATA
edsmapplotter-0.2.1.dist-info/WHEEL
edsmapplotter-0.2.1.dist-info/entry_points.txt
edsmapplotter-0.2.1.dist-info/top_level.txt
edsmapplotter-0.2.1.dist-info/RECORD
