Metadata-Version: 2.4
Name: edsmapplotter
Version: 0.2.1
Summary: A Python tool for automating EDS/EDX heatmap generation from microscopy data
Author-email: Fabio Dossi <fabio.dossi@example.com>
License: MIT
Project-URL: Homepage, https://github.com/fdossi/EDSMapPlotter
Project-URL: Repository, https://github.com/fdossi/EDSMapPlotter
Project-URL: Documentation, https://github.com/fdossi/EDSMapPlotter/blob/main/README.md
Project-URL: Bug Tracker, https://github.com/fdossi/EDSMapPlotter/issues
Keywords: EDS,EDX,microscopy,SEM,heatmap,materials-science
Classifier: Development Status :: 4 - Beta
Classifier: Intended Audience :: Science/Research
Classifier: Topic :: Scientific/Engineering :: Chemistry
Classifier: Topic :: Scientific/Engineering :: Physics
Classifier: Topic :: Scientific/Engineering :: Visualization
Classifier: License :: OSI Approved :: MIT License
Classifier: Programming Language :: Python :: 3
Classifier: Programming Language :: Python :: 3.7
Classifier: Programming Language :: Python :: 3.8
Classifier: Programming Language :: Python :: 3.9
Classifier: Programming Language :: Python :: 3.10
Classifier: Programming Language :: Python :: 3.11
Classifier: Programming Language :: Python :: 3.12
Classifier: Operating System :: OS Independent
Requires-Python: >=3.7
License-File: LICENSE
Requires-Dist: pandas>=1.3.0
Requires-Dist: numpy>=1.20.0
Requires-Dist: matplotlib>=3.3.0
Requires-Dist: Pillow>=8.0.0
Provides-Extra: gui
Requires-Dist: tkinterdnd2>=0.3.0; extra == "gui"
Provides-Extra: dev
Requires-Dist: build; extra == "dev"
Requires-Dist: twine; extra == "dev"
Requires-Dist: pytest; extra == "dev"
Dynamic: license-file
